LICENSE
README.md
setup.py
effect_size_analysis/__init__.py
effect_size_analysis/cliff_delta.py
effect_size_analysis.egg-info/PKG-INFO
effect_size_analysis.egg-info/SOURCES.txt
effect_size_analysis.egg-info/dependency_links.txt
effect_size_analysis.egg-info/requires.txt
effect_size_analysis.egg-info/top_level.txt