Metadata-Version: 2.1
Name: effect-size-analysis
Version: 0.1.0
Summary: Some affect size methods
Home-page: https://github.com/LeonardoAlchieri/affect-size
Author: Leonardo Alchieri
Author-email: leonardo@alchieri.eu
License: MIT
Keywords: effect,size,delta,cliff,confidence interval
Classifier: Programming Language :: Python
Classifier: Programming Language :: Python :: 3.6
Classifier: Programming Language :: Python :: 3.7
Classifier: Programming Language :: Python :: 3.8
Classifier: Programming Language :: Python :: 3.9
Classifier: Programming Language :: Python :: 3.10
Classifier: Programming Language :: Python :: 3.11
Classifier: Development Status :: 2 - Pre-Alpha
Classifier: Environment :: Console
Classifier: Intended Audience :: Developers
Classifier: License :: OSI Approved :: MIT License
Requires-Python: >=3.6
License-File: LICENSE
